pyslow5.cpython-39-x86_64-linux-gnu.so
pyslow5.libs/libzstd-895b04ca.so.1.3.1
pyslow5-1.3.1.dist-info/WHEEL
pyslow5-1.3.1.dist-info/LICENSE
pyslow5-1.3.1.dist-info/METADATA
pyslow5-1.3.1.dist-info/top_level.txt
pyslow5-1.3.1.dist-info/RECORD
