Metadata-Version: 2.1
Name: pyslow5
Version: 1.3.1
Summary: slow5lib python bindings
Home-page: https://github.com/hasindu2008/slow5lib
Author: Hasindu Gamaarachchi, Sasha Jenner, James Ferguson
Author-email: hasindu2008@gmail.com
Maintainer: Hasindu Gamaarachchi
Maintainer-email: hasindu2008@gmail.com
License: MIT
Keywords: nanopore,slow5,signal
Platform: UNKNOWN
Classifier: Development Status :: 5 - Production/Stable
Classifier: License :: OSI Approved :: MIT License
Classifier: Programming Language :: C
Classifier: Programming Language :: Cython
Classifier: Programming Language :: Python :: 3
Classifier: Intended Audience :: Science/Research
Classifier: Topic :: Scientific/Engineering :: Bio-Informatics
Requires-Python: >=3.4.3
